[["Map",1,2],"meta::meta",["Map",3,4,5,6],"astro-version","5.18.0","astro-config-digest","{\"root\":{},\"srcDir\":{},\"publicDir\":{},\"outDir\":{},\"cacheDir\":{},\"site\":\"https://branda.ist\",\"compressHTML\":true,\"base\":\"/\",\"trailingSlash\":\"ignore\",\"output\":\"static\",\"scopedStyleStrategy\":\"attribute\",\"build\":{\"format\":\"directory\",\"client\":{},\"server\":{},\"assets\":\"_astro\",\"serverEntry\":\"entry.mjs\",\"redirects\":true,\"inlineStylesheets\":\"auto\",\"concurrency\":1},\"server\":{\"open\":false,\"host\":false,\"port\":4321,\"streaming\":true,\"allowedHosts\":[]},\"redirects\":{\"/elementor-2359\":\"/\",\"/wp-content/plugins/litespeed-cache/guest.vary.php\":\"/\",\"/products.html\":\"/urunler\",\"/iletisim/urunler.html\":\"/urunler\",\"/hakkimizda/iletisim.html\":\"/iletisim\",\"/iletisim.html\":\"/iletisim\",\"/iletisim/hakkimizda.html\":\"/hakkimizda\",\"/hakkimizda.html\":\"/hakkimizda\",\"/hizmetler.html\":\"/hizmetler\",\"/fabrika-bolmeleri-kapilari\":\"/bolme-ve-kapi-brandasi\",\"/endustriyel-cadirlar\":\"/endustriyel-cadir\",\"/pergola-motorlu-tente\":\"/pergola-tente\",\"/hali-saha-cadiri\":\"/halisaha-spor-cadiri\",\"/ceset-torbasi-brandasi\":\"/urunler\",\"/kis-bahcesi-icin-seffaf-branda-secimi\":\"/blog/kis-bahcesi-icin-seffaf-branda-secimi\",\"/depo-cadiri-alirken-dikkat-edilmesi-gerekenler\":\"/blog/depo-cadiri-alirken-dikkat-edilmesi-gerekenler\",\"/kis-bahcesi-ruhsat-gerektirir-mi\":\"/blog/kis-bahcesi-ruhsat-gerektirir-mi\",\"/mafsalli-ile-kasetli-tente-farklari\":\"/blog/mafsalli-ile-kasetli-tente-farklari\",\"/motorlu-tente-arizalari-ve-cozumleri\":\"/blog/motorlu-tente-arizalari-ve-cozumleri\",\"/akrilik-mi-polyester-mi-secmeli\":\"/blog/akrilik-mi-polyester-mi-secmeli\",\"/depo-cadiri-nedir\":\"/blog/depo-cadiri-nedir\"},\"image\":{\"endpoint\":{\"route\":\"/_image\"},\"service\":{\"entrypoint\":\"astro/assets/services/sharp\",\"config\":{}},\"domains\":[],\"remotePatterns\":[],\"responsiveStyles\":false},\"devToolbar\":{\"enabled\":true},\"markdown\":{\"syntaxHighlight\":{\"type\":\"shiki\",\"excludeLangs\":[\"math\"]},\"shikiConfig\":{\"langs\":[],\"langAlias\":{},\"theme\":\"github-dark\",\"themes\":{},\"wrap\":false,\"transformers\":[]},\"remarkPlugins\":[],\"rehypePlugins\":[],\"remarkRehype\":{},\"gfm\":true,\"smartypants\":true},\"security\":{\"checkOrigin\":true,\"allowedDomains\":[],\"actionBodySizeLimit\":1048576},\"env\":{\"schema\":{},\"validateSecrets\":false},\"experimental\":{\"clientPrerender\":false,\"contentIntellisense\":false,\"headingIdCompat\":false,\"preserveScriptOrder\":false,\"liveContentCollections\":false,\"csp\":false,\"staticImportMetaEnv\":false,\"chromeDevtoolsWorkspace\":false,\"failOnPrerenderConflict\":false,\"svgo\":false},\"legacy\":{\"collections\":false}}"]